[
    {
        "Name": "Animal Instinct",
        "Description": "Animal Instinct is a Companion mod that gives Enemy Sense and Loot Detection effects to the companion's owner. It can be equipped on both Sentinels and Kubrows.[1] Unlike the equivalent Warframe auras (with which these effects stack), these effects only apply to the owner and not the other players in the squad, and they cease if the companion dies during the mission.",
        "Rarity": "Rare",
        "TraddingTax": "8,000",
        "URL": "http://warframe.wikia.com/wiki/Animal_Instinct",
        "Transmutable": true,
        "Ranks": 5,
        "ImageURL": "http://vignette2.wikia.nocookie.net/warframe/images/3/34/AnimalInstinctMod.png/revision/latest?cb=20160713125221",
        "Polarity": "Naramon",
        "Tradable": true,
        "DroppedBy": [
            {
                "Name": "Nightmare Mode Reward",
                "Links": [
                    "/wiki/Nightmare_Mode"
                ]
            },
            {
                "Name": "Tier 5-6 Platinum Packs",
                "Links": [
                    "/wiki/Platinum",
                    "https://warframe.com/buyplatinum"
                ]
            },
            {
                "Name": "Alerts",
                "Links": [
                    "/wiki/Alert"
                ]
            }
        ]
    },
    {
        "Name": "Bite",
        "Description": "Bite mod increases Kubrow and Kavat Critical Chance & Critical Damage.",
        "Rarity": "Rare",
        "TraddingTax": "8,000",
        "URL": "http://warframe.wikia.com/wiki/Bite",
        "Transmutable": true,
        "Ranks": 10,
        "ImageURL": "http://vignette2.wikia.nocookie.net/warframe/images/9/91/BiteMod.png/revision/latest?cb=20160713125221",
        "Polarity": "Madurai",
        "Tradable": true,
        "DroppedBy": [
            {
                "Name": "Drahk",
                "Links": [
                    "/wiki/Drahk"
                ]
            },
            {
                "Name": "Kubrow",
                "Links": [
                    "/wiki/Kubrow_"
                ]
            }
        ]
    },
    {
        "Name": "Dig",
        "Description": "The Dig mod allows the Sahasa Kubrow to dig up items upon the battlefield. They will be able to dig up random ammunition types, health orbs, energy orbs, small amounts of credits, and occasionally mods.",
        "Rarity": "Rare",
        "TraddingTax": "8,000",
        "URL": "http://warframe.wikia.com/wiki/Dig",
        "Transmutable": true,
        "Ranks": 5,
        "ImageURL": "http://vignette4.wikia.nocookie.net/warframe/images/6/66/DigModU145.png/revision/latest?cb=20140830023250",
        "Polarity": "Penjaga",
        "Tradable": true,
        "DroppedBy": [
            {
                "Name": "Drahk",
                "Links": [
                    "/wiki/Drahk"
                ]
            },
            {
                "Name": "Kubrow",
                "Links": [
                    "/wiki/Kubrow_"
                ]
            }
        ]
    },
    {
        "Name": "Hastened Deflection",
        "Description": "Hastened Deflection speeds up a Kubrow's shield regeneration rate. It has no effect on recharge delay.",
        "Rarity": "Uncommon",
        "TraddingTax": "4,000",
        "URL": "http://warframe.wikia.com/wiki/Fast_Deflection_(Kubrow)",
        "Transmutable": true,
        "Ranks": 5,
        "ImageURL": "http://vignette2.wikia.nocookie.net/warframe/images/c/c0/HastenedDeflectionMod.png/revision/latest?cb=20160531214922",
        "Polarity": "Vazarin",
        "Tradable": true,
        "DroppedBy": [
            {
                "Name": "Drahk",
                "Links": [
                    "/wiki/Drahk"
                ]
            },
            {
                "Name": "Kubrow",
                "Links": [
                    "/wiki/Kubrow_"
                ]
            }
        ]
    },
    {
        "Name": "Ferocity",
        "Description": "The Ferocity  mod allows the Sahasa Kubrow to use finisher attacks on enemies.",
        "Rarity": "Rare",
        "TraddingTax": "8,000",
        "URL": "http://warframe.wikia.com/wiki/Ferocity",
        "Transmutable": true,
        "Ranks": 5,
        "ImageURL": "http://vignette4.wikia.nocookie.net/warframe/images/b/b4/FerocityModU145.png/revision/latest?cb=20140830130608",
        "Polarity": "Penjaga",
        "Tradable": true,
        "DroppedBy": [
            {
                "Name": "Drahk",
                "Links": [
                    "/wiki/Drahk"
                ]
            },
            {
                "Name": "Kubrow",
                "Links": [
                    "/wiki/Kubrow_"
                ]
            }
        ]
    },
    {
        "Name": "Howl",
        "Description": "Howl mod allows Raksa Kubrow to cry out a blood-curdling howl to strike fear into its foes.",
        "Rarity": "Rare",
        "TraddingTax": "8,000",
        "URL": "http://warframe.wikia.com/wiki/Howl",
        "Transmutable": true,
        "Ranks": 5,
        "ImageURL": "http://vignette3.wikia.nocookie.net/warframe/images/6/64/Howl_19.6.3.png/revision/latest?cb=20170118032936",
        "Polarity": "Penjaga",
        "Tradable": true,
        "DroppedBy": [
            {
                "Name": "Drahk",
                "Links": [
                    "/wiki/Drahk"
                ]
            },
            {
                "Name": "Kubrow",
                "Links": [
                    "/wiki/Kubrow_"
                ]
            }
        ]
    },
    {
        "Name": "Hunt",
        "Description": "The Hunt  mod allows the Huras Kubrow to tackle a nearby opponent. The tackle can also hit multiple targets.",
        "Rarity": "Rare",
        "TraddingTax": "8,000",
        "URL": "http://warframe.wikia.com/wiki/Hunt",
        "Transmutable": true,
        "Ranks": 5,
        "ImageURL": "http://vignette2.wikia.nocookie.net/warframe/images/9/99/Hunt_19.6.3.png/revision/latest?cb=20170118032942",
        "Polarity": "Penjaga",
        "Tradable": true,
        "DroppedBy": [
            {
                "Name": "Drahk",
                "Links": [
                    "/wiki/Drahk"
                ]
            },
            {
                "Name": "Kubrow",
                "Links": [
                    "/wiki/Kubrow_"
                ]
            }
        ]
    },
    {
        "Name": "Link Armor",
        "Description": "Link Armor is a Companion mod that provides a bonus to companion armor, scaled off of warframe armor.",
        "Rarity": "Uncommon",
        "TraddingTax": "4,000",
        "URL": "http://warframe.wikia.com/wiki/Link_Armor",
        "Transmutable": true,
        "Ranks": 10,
        "ImageURL": "http://vignette3.wikia.nocookie.net/warframe/images/1/15/LinkArmorMod.png/revision/latest?cb=20160713125223",
        "Polarity": "Vazarin",
        "Tradable": true,
        "DroppedBy": [
            {
                "Name": "Drahk",
                "Links": [
                    "/wiki/Drahk"
                ]
            },
            {
                "Name": "Kubrow",
                "Links": [
                    "/wiki/Kubrow_"
                ]
            }
        ]
    },
    {
        "Name": "Link Health",
        "Description": "Link Health is a Companion mod that increases its health based on a percentage of the player's health. The player's health is unaffected by this mod.",
        "Rarity": "Uncommon",
        "TraddingTax": "4,000",
        "URL": "http://warframe.wikia.com/wiki/Link_Health",
        "Transmutable": true,
        "Ranks": 10,
        "ImageURL": "http://vignette4.wikia.nocookie.net/warframe/images/8/83/LinkHealthMod.png/revision/latest?cb=20160713125223",
        "Polarity": "Vazarin",
        "Tradable": true,
        "DroppedBy": [
            {
                "Name": "Drahk",
                "Links": [
                    "/wiki/Drahk"
                ]
            },
            {
                "Name": "Kubrow",
                "Links": [
                    "/wiki/Kubrow_"
                ]
            }
        ]
    },
    {
        "Name": "Link Shields",
        "Description": "Link Shields increases a Kubrow's maximum shields by adding a percent of the Warframe's shields to its own shields.",
        "Rarity": "Uncommon",
        "TraddingTax": "4,000",
        "URL": "http://warframe.wikia.com/wiki/Link_Shields",
        "Transmutable": true,
        "Ranks": 10,
        "ImageURL": "http://vignette1.wikia.nocookie.net/warframe/images/5/54/LinkShieldsMod.png/revision/latest?cb=20160713125226",
        "Polarity": "Vazarin",
        "Tradable": true,
        "DroppedBy": [
            {
                "Name": "Drahk",
                "Links": [
                    "/wiki/Drahk"
                ]
            },
            {
                "Name": "Kubrow",
                "Links": [
                    "/wiki/Kubrow_"
                ]
            }
        ]
    },
    {
        "Name": "Loyal Companion",
        "Description": "Loyal Companion is a Kubrow and Kavat mod that allows the owner to share their Bleedout time as an extension to their companion's Bleedout time.",
        "Rarity": "Common",
        "TraddingTax": "2,000",
        "URL": "http://warframe.wikia.com/wiki/Loyal_Companion",
        "Transmutable": true,
        "Ranks": 5,
        "ImageURL": "http://vignette2.wikia.nocookie.net/warframe/images/1/10/LoyalCompanionMod.png/revision/latest?cb=20160713125226",
        "Polarity": "Vazarin",
        "Tradable": true,
        "DroppedBy": [
            {
                "Name": "Drahk",
                "Links": [
                    "/wiki/Drahk"
                ]
            },
            {
                "Name": "Kubrow",
                "Links": [
                    "/wiki/Kubrow_"
                ]
            }
        ]
    },
    {
        "Name": "Maul",
        "Description": "Maul mod increases the melee damage a Kubrow or Kavat deals by 30% per rank to a maximum of 330% at rank 10.",
        "Rarity": "Uncommon",
        "TraddingTax": "4,000",
        "URL": "http://warframe.wikia.com/wiki/Maul",
        "Transmutable": true,
        "Ranks": 10,
        "ImageURL": "http://vignette3.wikia.nocookie.net/warframe/images/0/0e/MaulMod.png/revision/latest?cb=20160713125222",
        "Polarity": "Madurai",
        "Tradable": true,
        "DroppedBy": [
            {
                "Name": "Drahk",
                "Links": [
                    "/wiki/Drahk"
                ]
            },
            {
                "Name": "Kubrow",
                "Links": [
                    "/wiki/Kubrow_"
                ]
            }
        ]
    },
    {
        "Name": "Neutralize",
        "Description": "Neutralize is a Kubrow exclusive mod that allows the Chesa Kubrow to disarm enemies.",
        "Rarity": "Rare",
        "TraddingTax": "8,000",
        "URL": "http://warframe.wikia.com/wiki/Neutralize",
        "Transmutable": false,
        "Ranks": 5,
        "ImageURL": "http://vignette4.wikia.nocookie.net/warframe/images/2/28/Neutralize_19.6.3.png/revision/latest?cb=20170118032939",
        "Polarity": "Penjaga",
        "Tradable": true,
        "DroppedBy": [
            {
                "Name": "Transmutable",
                "Links": [
                    "/wiki/Transmutation"
                ]
            }
        ]
    },
    {
        "Name": "Pack Leader",
        "Description": "Pack Leader is a mod that heals an incubated companion by a percentage of the damage dealt by a player with melee attacks.",
        "Rarity": "Common",
        "TraddingTax": "2,000",
        "URL": "http://warframe.wikia.com/wiki/Pack_Leader",
        "Transmutable": true,
        "Ranks": 5,
        "ImageURL": "http://vignette3.wikia.nocookie.net/warframe/images/a/a2/PackLeaderMod.png/revision/latest?cb=20160713125222",
        "Polarity": "Madurai",
        "Tradable": true,
        "DroppedBy": [
            {
                "Name": "Drahk",
                "Links": [
                    "/wiki/Drahk"
                ]
            },
            {
                "Name": "Kubrow",
                "Links": [
                    "/wiki/Kubrow_"
                ]
            }
        ]
    },
    {
        "Name": "Protect",
        "Description": "Protect mod allows Raksa Kubrow to come to the defense of its master, replenishing both their shields and its own.",
        "Rarity": "Rare",
        "TraddingTax": "8,000",
        "URL": "http://warframe.wikia.com/wiki/Protect",
        "Transmutable": true,
        "Ranks": 5,
        "ImageURL": "http://vignette3.wikia.nocookie.net/warframe/images/4/40/Protect_19.6.3.png/revision/latest?cb=20170118032934",
        "Polarity": "Penjaga",
        "Tradable": true,
        "DroppedBy": [
            {
                "Name": "Drahk",
                "Links": [
                    "/wiki/Drahk"
                ]
            },
            {
                "Name": "Kubrow",
                "Links": [
                    "/wiki/Kubrow_"
                ]
            }
        ]
    },
    {
        "Name": "Retrieve",
        "Description": "Retrieve is a Kubrow exclusive mod that allows the Chesa Kubrow to retrieve items.",
        "Rarity": "Common",
        "TraddingTax": "2,000",
        "URL": "http://warframe.wikia.com/wiki/Retrieve",
        "Transmutable": false,
        "Ranks": 5,
        "ImageURL": "http://vignette1.wikia.nocookie.net/warframe/images/8/86/Retrieve_19.6.3.png/revision/latest?cb=20170118032940",
        "Polarity": "Penjaga",
        "Tradable": true,
        "DroppedBy": [
            {
                "Name": "Transmutable",
                "Links": [
                    "/wiki/Transmutation"
                ]
            }
        ]
    },
    {
        "Name": "Savagery",
        "Description": "Savagery mod allows the Sunika Kubrow to overwhelm its prey with a powerful finisher attack.",
        "Rarity": "Rare",
        "TraddingTax": "8,000",
        "URL": "http://warframe.wikia.com/wiki/Savagery",
        "Transmutable": true,
        "Ranks": 5,
        "ImageURL": "http://vignette1.wikia.nocookie.net/warframe/images/d/db/SavageryModU145.png/revision/latest?cb=20140901144536",
        "Polarity": "Penjaga",
        "Tradable": true,
        "DroppedBy": [
            {
                "Name": "Drahk",
                "Links": [
                    "/wiki/Drahk"
                ]
            },
            {
                "Name": "Kubrow",
                "Links": [
                    "/wiki/Kubrow_"
                ]
            }
        ]
    },
    {
        "Name": "Shelter",
        "Description": "Shelter allows a Kubrow to create a Shield around its master while they revive fallen Allies.",
        "Rarity": "Uncommon",
        "TraddingTax": "4,000",
        "URL": "http://warframe.wikia.com/wiki/Shelter",
        "Transmutable": true,
        "Ranks": 10,
        "ImageURL": "http://vignette4.wikia.nocookie.net/warframe/images/0/06/Shelter_19.6.3.png/revision/latest?cb=20170118032932",
        "Polarity": "Vazarin",
        "Tradable": true,
        "DroppedBy": [
            {
                "Name": "Drahk",
                "Links": [
                    "/wiki/Drahk"
                ]
            },
            {
                "Name": "Kubrow",
                "Links": [
                    "/wiki/Kubrow_"
                ]
            }
        ]
    },
    {
        "Name": "Scavenge",
        "Description": "Scavenge mod gives Kubrows and Kavats a chance to unlock lockers.",
        "Rarity": "Common",
        "TraddingTax": "2,000",
        "URL": "http://warframe.wikia.com/wiki/Scavenge",
        "Transmutable": true,
        "Ranks": 5,
        "ImageURL": "http://vignette1.wikia.nocookie.net/warframe/images/4/4f/ScavengeMod.png/revision/latest?cb=20160713125227",
        "Polarity": "Penjaga",
        "Tradable": true,
        "DroppedBy": [
            {
                "Name": "Drahk",
                "Links": [
                    "/wiki/Drahk"
                ]
            },
            {
                "Name": "Kubrow",
                "Links": [
                    "/wiki/Kubrow_"
                ]
            }
        ]
    },
    {
        "Name": "Stalk",
        "Description": "The Stalk mod allows the Huras Kubrow to cloak itself and its master when hostile entities are within range, similar to Shade's Ghost Precept.",
        "Rarity": "Rare",
        "TraddingTax": "8,000",
        "URL": "http://warframe.wikia.com/wiki/Stalk",
        "Transmutable": true,
        "Ranks": 5,
        "ImageURL": "http://vignette3.wikia.nocookie.net/warframe/images/3/34/Stalk_19.6.3.png/revision/latest?cb=20170118032937",
        "Polarity": "Penjaga",
        "Tradable": true,
        "DroppedBy": [
            {
                "Name": "Drahk",
                "Links": [
                    "/wiki/Drahk"
                ]
            },
            {
                "Name": "Kubrow",
                "Links": [
                    "/wiki/Kubrow_"
                ]
            }
        ]
    },
    {
        "Name": "Unleashed",
        "Description": "The  Unleashed  mod allows the Sunika Kubrow to grapple a VIP target, forcing them to the ground.",
        "Rarity": "Rare",
        "TraddingTax": "8,000",
        "URL": "http://warframe.wikia.com/wiki/Unleashed",
        "Transmutable": true,
        "Ranks": 5,
        "ImageURL": "http://vignette1.wikia.nocookie.net/warframe/images/6/6d/Unleashed_19.6.3.png/revision/latest?cb=20170118032930",
        "Polarity": "Penjaga",
        "Tradable": true,
        "DroppedBy": [
            {
                "Name": "Drahk",
                "Links": [
                    "/wiki/Drahk"
                ]
            },
            {
                "Name": "Kubrow",
                "Links": [
                    "/wiki/Kubrow_"
                ]
            }
        ]
    }
]
